Metadata-Version: 2.1
Name: traxex
Version: 0.0.3
Summary: Quick schedule for competitive DotA 2 Tournaments.
Home-page: https://github.com/sinkaroid/traxex.py
Author: sinkaroid
Author-email: anakmancasan@gmail.com
License: MIT
Keywords: dota 2,wrapper,liquipedia
Platform: UNKNOWN
